AUTHORS
MANIFEST.in
README.rst
setup.py
pymonon/__init__.py
pymonon/currencies.py
pymonon.egg-info/PKG-INFO
pymonon.egg-info/SOURCES.txt
pymonon.egg-info/dependency_links.txt
pymonon.egg-info/top_level.txt