Metadata-Version: 1.1
Name: pymonon
Version: 0.0.1-dev
Summary: Python Money Helper
Home-page: https://github.com/pedroburon/pymonon
Author: Pedro Buron
Author-email: pedroburonv@gmail.com
License: UNKNOWN
Platform: UNKNOWN
Classifier: Development Status :: 1 - Planning
Classifier: Programming Language :: Python :: 2 :: Only
Classifier: Topic :: Software Development :: Libraries :: Python Modules
Classifier: Topic :: Office/Business :: Financial :: Accounting
